setup.py
boycesdk/__init__.py
boycesdk/help.py
boycesdk.egg-info/PKG-INFO
boycesdk.egg-info/SOURCES.txt
boycesdk.egg-info/dependency_links.txt
boycesdk.egg-info/entry_points.txt
boycesdk.egg-info/top_level.txt