Metadata-Version: 1.0
Name: boycesdk
Version: 0.0.3
Summary: boyce sdk
Home-page: http://www.keepstudying.club
Author: boyce
Author-email: 120674007@qq.com
License: MIT Licence
Platform: any
